beagle/__init__.py
beagle/app.py
beagle/grep_formatter.py
beagle/hound.py
beagle/openstack.py
beagle/search.py
beagle-0.5.0.dist-info/METADATA
beagle-0.5.0.dist-info/WHEEL
beagle-0.5.0.dist-info/entry_points.txt
beagle-0.5.0.dist-info/licenses/LICENSE
beagle-0.5.0.dist-info/RECORD
